azure/mgmt/managedapplications/__init__.py
azure/mgmt/managedapplications/_configuration.py
azure/mgmt/managedapplications/_managed_applications_mgmt_client.py
azure/mgmt/managedapplications/_patch.py
azure/mgmt/managedapplications/_serialization.py
azure/mgmt/managedapplications/_vendor.py
azure/mgmt/managedapplications/_version.py
azure/mgmt/managedapplications/py.typed
azure/mgmt/managedapplications/aio/__init__.py
azure/mgmt/managedapplications/aio/_configuration.py
azure/mgmt/managedapplications/aio/_managed_applications_mgmt_client.py
azure/mgmt/managedapplications/aio/_patch.py
azure/mgmt/managedapplications/aio/_vendor.py
azure/mgmt/managedapplications/aio/operations/__init__.py
azure/mgmt/managedapplications/aio/operations/_application_definitions_operations.py
azure/mgmt/managedapplications/aio/operations/_applications_operations.py
azure/mgmt/managedapplications/aio/operations/_jit_requests_operations.py
azure/mgmt/managedapplications/aio/operations/_managed_applications_mgmt_client_operations.py
azure/mgmt/managedapplications/aio/operations/_patch.py
azure/mgmt/managedapplications/models/__init__.py
azure/mgmt/managedapplications/models/_managed_applications_mgmt_client_enums.py
azure/mgmt/managedapplications/models/_models_py3.py
azure/mgmt/managedapplications/models/_patch.py
azure/mgmt/managedapplications/operations/__init__.py
azure/mgmt/managedapplications/operations/_application_definitions_operations.py
azure/mgmt/managedapplications/operations/_applications_operations.py
azure/mgmt/managedapplications/operations/_jit_requests_operations.py
azure/mgmt/managedapplications/operations/_managed_applications_mgmt_client_operations.py
azure/mgmt/managedapplications/operations/_patch.py
azure_mgmt_managedapplications-1.0.0b1.dist-info/LICENSE
azure_mgmt_managedapplications-1.0.0b1.dist-info/METADATA
azure_mgmt_managedapplications-1.0.0b1.dist-info/WHEEL
azure_mgmt_managedapplications-1.0.0b1.dist-info/top_level.txt
azure_mgmt_managedapplications-1.0.0b1.dist-info/RECORD
